{
  "created": "2026-04-22",
  "updated": "2026-04-22",
  "sources": [
    {
      "id": "repo-readme",
      "path": "../README.md",
      "type": "repository-doc",
      "status": "referenced",
      "notes": "Primary public project overview and install notes."
    },
    {
      "id": "release-checklist",
      "path": "../RELEASING_BENTERM.md",
      "type": "repository-doc",
      "status": "referenced",
      "notes": "Release checklist and optional package-manager publishing policy."
    },
    {
      "id": "release-notes",
      "path": "../RELEASE_NOTES_BENTERM.md",
      "type": "repository-doc",
      "status": "referenced",
      "notes": "Draft release notes for the cross-platform BENTERM release."
    }
  ]
}
